sequoia/__init__.py
sequoia/sequoia.py
sequoia/server.py
sequoia-0.0.10.dist-info/METADATA
sequoia-0.0.10.dist-info/WHEEL
sequoia-0.0.10.dist-info/top_level.txt
sequoia-0.0.10.dist-info/RECORD
