Metadata-Version: 2.1
Name: sequoia
Version: 0.0.10
Summary: An awesome package that does something
Home-page: http://pypi.python.org/pypi/PackageName/
Author: An Awesome Coder
Author-email: hanirizo@gmail.com
License: LICENSE.txt
Requires-Dist: urllib3 (==1.26.13)
Requires-Dist: fastapi (==0.75.1)
Requires-Dist: sentry-sdk (==1.5.12)
Requires-Dist: SQLAlchemy (==2.0.0b4)
Requires-Dist: psycopg2-binary (==2.9.3)
Requires-Dist: uvicorn (==0.17.6)
Requires-Dist: PyJWT (==2.3.0)
Requires-Dist: passlib (==1.7.4)
Requires-Dist: bugsnag (==4.2.1)
Requires-Dist: bcrypt (==3.2.0)
Requires-Dist: python-slugify (==6.1.2)
Requires-Dist: redis (==4.3.4)
Requires-Dist: dnspython (==2.2.1)
Requires-Dist: requests (==2.28.1)
Requires-Dist: google-cloud-pubsub (==2.8.0)
Requires-Dist: python-dotenv (==0.21.0)
Requires-Dist: boto3 (==1.24.80)
Requires-Dist: toml (==0.10.2)
Requires-Dist: python-multipart (==0.0.5)
Requires-Dist: pydantic (==1.8.2)
Requires-Dist: pydantic[email]
Requires-Dist: device-detector (==5.0.1)
Requires-Dist: pandas (==1.5.0)
Requires-Dist: openpyxl (==3.0.10)
Requires-Dist: munch (==2.5.0)
Requires-Dist: pymongo (==4.2.0)
Requires-Dist: click (==8.1.3)
Requires-Dist: asyncpg (==0.27.0)
Requires-Dist: ujson (==5.5.0)
Requires-Dist: aioredis (==2.0.1)
Requires-Dist: schedule (==1.1.0)
Requires-Dist: slowapi (==0.1.7)
